{
  "docusaurus-plugin-content-docs": {
    "default": {
      "path": "/docs",
      "versions": [
        {
          "name": "current",
          "label": "Next",
          "isLast": true,
          "path": "/docs",
          "mainDocId": "intro",
          "docs": [
            {
              "id": "activation-api-keys/activation",
              "path": "/docs/activation-api-keys/activation",
              "sidebar": "tutorialSidebar"
            },
            {
              "id": "authors/authors_markdown",
              "path": "/docs/authors/authors_markdown",
              "sidebar": "tutorialSidebar"
            },
            {
              "id": "contributing/acknowledgements",
              "path": "/docs/contributing/acknowledgements",
              "sidebar": "tutorialSidebar"
            },
            {
              "id": "contributing/contributing_markdown",
              "path": "/docs/contributing/contributing_markdown",
              "sidebar": "tutorialSidebar"
            },
            {
              "id": "intro",
              "path": "/docs/intro",
              "sidebar": "tutorialSidebar"
            },
            {
              "id": "/category/how-to-activate-keys",
              "path": "/docs/category/how-to-activate-keys",
              "sidebar": "tutorialSidebar"
            }
          ],
          "draftIds": [],
          "sidebars": {
            "tutorialSidebar": {
              "link": {
                "path": "/docs/intro",
                "label": "intro"
              }
            }
          }
        }
      ],
      "breadcrumbs": true
    }
  }
}